setup.py
clef/__init__.py
clef/clef.py
clef.egg-info/PKG-INFO
clef.egg-info/SOURCES.txt
clef.egg-info/dependency_links.txt
clef.egg-info/pbr.json
clef.egg-info/requires.txt
clef.egg-info/top_level.txt