Metadata-Version: 1.1
Name: clef
Version: 0.0.8
Summary: A Python wrapper for the Clef API
Home-page: https://github.com/gwongz/clef-python
Author: Grace Wong
Author-email: gwongz@gmail.com
License: MIT
Download-URL: https://github.com/gwongz/python-clef/tarball/0.0.8
Keywords: clef,api
Platform: UNKNOWN
Classifier: Natural Language :: English
Classifier: Intended Audience :: Developers
Classifier: License :: OSI Approved :: MIT License
Classifier: Operating System :: OS Independent
Classifier: Programming Language :: Python
Classifier: Programming Language :: Python :: 2.7
Classifier: Topic :: Software Development :: Libraries :: Python Modules
